langchain_sandbox/__init__.py
langchain_sandbox/py.typed
langchain_sandbox/pyodide.py
langchain_sandbox-0.0.6.dist-info/METADATA
langchain_sandbox-0.0.6.dist-info/WHEEL
langchain_sandbox-0.0.6.dist-info/RECORD
