Metadata-Version: 2.4
Name: langchain_sandbox
Version: 0.0.6
Summary: LangChain Sandbox
Requires-Python: >=3.10
Requires-Dist: langchain-core<0.4.0,>=0.3.56
Requires-Dist: langgraph>=0.4.3
